50_rtl/day7-HA&FA/full.v
module fulladder(input a,b,cin,output sum,carry);

assign sum=a^b^cin;
assign carry=(a&b) | (a^b)&cin;

endmodule

50_rtl/day7-HA&FA/full_tb.v
module test();
reg a,b,cin;
wire sum,carry;
reg clk;


fulladder dut(a,b,cin,sum,carry);

always #5 clk=~clk;

initial
begin
	$dumpfile("full.vcd");
	$dumpvars(0,test);
	clk=0;

	a=0;b=0;cin=0;
	#10;
	a=0;b=0;cin=1;
	#10;
	a=0;b=1;cin=0;
	#10;
	a=0;b=1;cin=1;
	#10;
	a=1;b=0;cin=0;
	#10;
	a=1;b=0;cin=1;
	#10;
	a=1;b=1;cin=0;
	#10;
	a=1;b=1;cin=1;
	#10;
	$finish;
	end
	
	
	always@(posedge clk)
	begin
	
$display("a=%b,b=%b,cin=%b,sum=%b,carry=%b",a,b,cin,sum,carry);
	end
	endmodule

50_rtl/day7-HA&FA/full.vcd
$date
	Tue Jul 18 00:07:12 2023
$end
$version
	Icarus Verilog
$end
$timescale
	1s
$end
$scope module test $end
$var wire 1 ! sum $end
$var wire 1 " carry $end
$var reg 1 # a $end
$var reg 1 $ b $end
$var reg 1 % cin $end
$var reg 1 & clk $end
$scope module dut $end
$var wire 1 # a $end
$var wire 1 $ b $end
$var wire 1 " carry $end
$var wire 1 % cin $end
$var wire 1 ! sum $end
$upscope $end
$upscope $end
$enddefinitions $end
#0
$dumpvars
0&
0%
0$
0#
0"
0!
$end
#5
1&
#10
1!
0&
1%
#15
1&
#20
0&
0%
1$
#25
1&
#30
1"
0!
0&
1%
#35
1&
#40
0"
1!
0&
0%
0$
1#
#45
1&
#50
1"
0!
0&
1%
#55
1&
#60
0&
0%
1$
#65
1&
#70
1!
0&
1%
