50_rtl/day7-HA&FA/FAuHA.v
module half(input a,b,output sum,carry);
assign sum=a^b;
assign carry=a&b;
endmodule


module FA(input a,b,cin,output s,c);
wire t1,t2,t3;
half h1(a,b,t1,t2);
half h2(t1,cin,s,t3);
assign c=t3|t2;
endmodule

50_rtl/day7-HA&FA/FAuHA_tb.v
module test();
reg a,b,cin;
wire sum,carry;
reg clk;


FA dut(a,b,cin,s,c);

always #5 clk=~clk;

initial
begin
	$dumpfile("FULL.vcd");
	$dumpvars(0,test);
	clk=0;

	a=0;b=0;cin=0;
	#10;
	a=0;b=0;cin=1;
	#10;
	a=0;b=1;cin=0;
	#10;
	a=0;b=1;cin=1;
	#10;
	a=1;b=0;cin=0;
	#10;
	a=1;b=0;cin=1;
	#10;
	a=1;b=1;cin=0;
	#10;
	a=1;b=1;cin=1;
	#10;
	$finish;
	end
	
	
	always@(posedge clk)
	begin
	
$display("a=%b,b=%b,cin=%b,s=%b,c=%b",a,b,cin,s,c);
	end
	endmodule

50_rtl/day7-HA&FA/FULL.vcd
$date
	Mon Jul 24 21:28:40 2023
$end
$version
	Icarus Verilog
$end
$timescale
	1s
$end
$scope module test $end
$var wire 1 ! s $end
$var wire 1 " c $end
$var reg 1 # a $end
$var reg 1 $ b $end
$var reg 1 % cin $end
$var reg 1 & clk $end
$scope module dut $end
$var wire 1 # a $end
$var wire 1 $ b $end
$var wire 1 " c $end
$var wire 1 % cin $end
$var wire 1 ' t3 $end
$var wire 1 ( t2 $end
$var wire 1 ) t1 $end
$var wire 1 ! s $end
$scope module h1 $end
$var wire 1 # a $end
$var wire 1 $ b $end
$var wire 1 ( carry $end
$var wire 1 ) sum $end
$upscope $end
$scope module h2 $end
$var wire 1 ) a $end
$var wire 1 % b $end
$var wire 1 ' carry $end
$var wire 1 ! sum $end
$upscope $end
$upscope $end
$upscope $end
$enddefinitions $end
#0
$dumpvars
0)
0(
0'
0&
0%
0$
0#
0"
0!
$end
#5
1&
#10
1!
0&
1%
#15
1&
#20
1)
0&
0%
1$
#25
1&
#30
1"
0!
1'
0&
1%
#35
1&
#40
0"
1!
0'
0&
0%
0$
1#
#45
1&
#50
1"
0!
1'
0&
1%
#55
1&
#60
0'
0)
1(
0&
0%
1$
#65
1&
#70
1!
0&
1%
