50_rtl/day9-ha,fa,hs,fs using nand/fs.v
module fs(input a,b,cin,output D,B);
wire [6:0]w;


nand n0(w[0],a,b);
nand n1(w[1],a,w[0]);
nand n2(w[2],b,w[0]);
nand n3(w[3],w[1],w[2]);
nand n4(w[4],cin,w[3]);
nand n5(w[5],w[3],w[4]);
nand n6(w[6],cin,w[4]);
nand n7(D,w[5],w[6]);
nand n8(B,w[2],w[6]);
endmodule

50_rtl/day9-ha,fa,hs,fs using nand/fs_tb.v
module test();
reg a,b,cin;
wire D,B;
reg clk;
fs dut(a,b,cin,D,B);

always #5 clk=~clk;


initial begin
	clk=0;
$dumpfile("fs.vcd");
$dumpvars(0,test);
	
	a=0;b=0;cin=0;
	#10;
	b=0;cin=1;
	#10;
	b=1;cin=0;
	#10;
	b=1;cin=1;
	#10 
	a=1;b=0;cin=0;
	#10;
	cin=1;
	#10;
	b=1;cin=0;
	#10 
	cin=1;
	
	#10$finish;
end

always @(posedge clk)
begin
	$display("a=%b,b=%b,cin=%b,D=%b,B=%b",a,b,cin,D,B);
end

endmodule

50_rtl/day9-ha,fa,hs,fs using nand/fs.vcd
$date
	Mon Jul 24 23:00:36 2023
$end
$version
	Icarus Verilog
$end
$timescale
	1s
$end
$scope module test $end
$var wire 1 ! D $end
$var wire 1 " B $end
$var reg 1 # a $end
$var reg 1 $ b $end
$var reg 1 % cin $end
$var reg 1 & clk $end
$scope module dut $end
$var wire 1 " B $end
$var wire 1 ! D $end
$var wire 1 # a $end
$var wire 1 $ b $end
$var wire 1 % cin $end
$var wire 7 ' w [6:0] $end
$upscope $end
$upscope $end
$enddefinitions $end
#0
$dumpvars
b1110111 '
0&
0%
0$
0#
0"
0!
$end
#5
1&
#10
1!
1"
b110111 '
0&
1%
#15
1&
#20
1!
b1011011 '
0&
0%
1$
#25
1&
#30
0!
b1101011 '
0&
1%
#35
1&
#40
1!
0"
b1011101 '
0&
0%
0$
1#
#45
1&
#50
0!
0"
b1101101 '
0&
1%
#55
1&
#60
0!
0"
b1110110 '
0&
0%
1$
#65
1&
#70
1!
1"
b110110 '
0&
1%
