50_rtl/day8-HS/hs.v
module hs(input a,b,output d,B);
assign d=a^b;
assign B=(~a)&b;
endmodule




module fs(input a,b,cin,output D,B);

wire t1,t2,t3;
hs c1(a,b,t1,t2);
hs c2(t1,cin,D,t3);
assign B=t3|t2;
endmodule

50_rtl/day8-HS/hs_tb.v
module test();
reg a,b,cin;
wire D,B;
reg clk;


fs dut(a,b,cin,D,B);

always #5 clk=~clk;

initial
begin
	$dumpfile("fs.vcd");
	$dumpvars(0,test);
	clk=0;

	a=0;b=0;cin=0;
	#10;
	a=0;b=0;cin=1;
	#10;
	a=0;b=1;cin=0;
	#10;
	a=0;b=1;cin=1;
	#10;
	a=1;b=0;cin=0;
	#10;
	a=1;b=0;cin=1;
	#10;
	a=1;b=1;cin=0;
	#10;
	a=1;b=1;cin=1;
	#10;
	$finish;
	end
	
	
	always@(posedge clk)
	begin
	
$display("a=%b,b=%b,cin=%b,D=%b,B=%b",a,b,cin,D,B);
	end
	endmodule

50_rtl/day8-HS/fs.vcd
$date
	Mon Jul 24 21:38:24 2023
$end
$version
	Icarus Verilog
$end
$timescale
	1s
$end
$scope module test $end
$var wire 1 ! D $end
$var wire 1 " B $end
$var reg 1 # a $end
$var reg 1 $ b $end
$var reg 1 % cin $end
$var reg 1 & clk $end
$scope module dut $end
$var wire 1 " B $end
$var wire 1 # a $end
$var wire 1 $ b $end
$var wire 1 % cin $end
$var wire 1 ' t3 $end
$var wire 1 ( t2 $end
$var wire 1 ) t1 $end
$var wire 1 ! D $end
$scope module c1 $end
$var wire 1 ( B $end
$var wire 1 # a $end
$var wire 1 $ b $end
$var wire 1 ) d $end
$upscope $end
$scope module c2 $end
$var wire 1 ' B $end
$var wire 1 ) a $end
$var wire 1 % b $end
$var wire 1 ! d $end
$upscope $end
$upscope $end
$upscope $end
$enddefinitions $end
#0
$dumpvars
0)
0(
0'
0&
0%
0$
0#
0"
0!
$end
#5
1&
#10
1"
1!
1'
0&
1%
#15
1&
#20
0'
1)
1(
0&
0%
1$
#25
1&
#30
0!
0&
1%
#35
1&
#40
0"
1!
0(
0&
0%
0$
1#
#45
1&
#50
0!
0&
1%
#55
1&
#60
0)
0&
0%
1$
#65
1&
#70
1"
1!
1'
0&
1%
